tt/__init__.py
tt/demo.py
GkSecondDemo-0.0.1.dist-info/METADATA
GkSecondDemo-0.0.1.dist-info/WHEEL
GkSecondDemo-0.0.1.dist-info/top_level.txt
GkSecondDemo-0.0.1.dist-info/RECORD
